{
  "generatedAt": "2026-05-29T09:15:08.642Z",
  "generator": "scripts/generate-docs-manifest.ts",
  "mounts": [
    {
      "routerVar": "authRouter",
      "mount": "/api/auth",
      "module": "auth"
    },
    {
      "routerVar": "profileRouter",
      "mount": "/api/profile",
      "module": "profile"
    },
    {
      "routerVar": "diningRouter",
      "mount": "/api/dining",
      "module": "dining"
    },
    {
      "routerVar": "admissionRouter",
      "mount": "/api/admission",
      "module": "admission"
    },
    {
      "routerVar": "inventoryRouter",
      "mount": "/api/inventory",
      "module": "inventory"
    },
    {
      "routerVar": "financeRouter",
      "mount": "/api/finance",
      "module": "finance"
    },
    {
      "routerVar": "notificationsRouter",
      "mount": "/api/notifications",
      "module": "notifications"
    }
  ],
  "routeCount": 69,
  "routes": [
    {
      "method": "POST",
      "path": "/allocate",
      "fullPath": "/api/admission/allocate",
      "module": "admission",
      "sourceFile": "src/modules/admission/admission.routes.ts"
    },
    {
      "method": "GET",
      "path": "/applications",
      "fullPath": "/api/admission/applications",
      "module": "admission",
      "sourceFile": "src/modules/admission/admission.routes.ts"
    },
    {
      "method": "POST",
      "path": "/applications/:id/seat-charge",
      "fullPath": "/api/admission/applications/:id/seat-charge",
      "module": "admission",
      "sourceFile": "src/modules/admission/admission.routes.ts"
    },
    {
      "method": "POST",
      "path": "/apply",
      "fullPath": "/api/admission/apply",
      "module": "admission",
      "sourceFile": "src/modules/admission/admission.routes.ts"
    },
    {
      "method": "GET",
      "path": "/my-status",
      "fullPath": "/api/admission/my-status",
      "module": "admission",
      "sourceFile": "src/modules/admission/admission.routes.ts"
    },
    {
      "method": "PATCH",
      "path": "/review/:id/",
      "fullPath": "/api/admission/review/:id/",
      "module": "admission",
      "sourceFile": "src/modules/admission/admission.routes.ts"
    },
    {
      "method": "GET",
      "path": "/admin/approve",
      "fullPath": "/api/auth/admin/approve",
      "module": "auth",
      "sourceFile": "src/modules/auth/auth.routes.ts"
    },
    {
      "method": "PATCH",
      "path": "/admin/approve",
      "fullPath": "/api/auth/admin/approve",
      "module": "auth",
      "sourceFile": "src/modules/auth/auth.routes.ts"
    },
    {
      "method": "POST",
      "path": "/admin/login",
      "fullPath": "/api/auth/admin/login",
      "module": "auth",
      "sourceFile": "src/modules/auth/auth.routes.ts"
    },
    {
      "method": "POST",
      "path": "/admin/register",
      "fullPath": "/api/auth/admin/register",
      "module": "auth",
      "sourceFile": "src/modules/auth/auth.routes.ts"
    },
    {
      "method": "GET",
      "path": "/devices",
      "fullPath": "/api/auth/devices",
      "module": "auth",
      "sourceFile": "src/modules/auth/auth.routes.ts"
    },
    {
      "method": "DELETE",
      "path": "/devices/:sessionId",
      "fullPath": "/api/auth/devices/:sessionId",
      "module": "auth",
      "sourceFile": "src/modules/auth/auth.routes.ts"
    },
    {
      "method": "POST",
      "path": "/login",
      "fullPath": "/api/auth/login",
      "module": "auth",
      "sourceFile": "src/modules/auth/auth.routes.ts"
    },
    {
      "method": "POST",
      "path": "/logout",
      "fullPath": "/api/auth/logout",
      "module": "auth",
      "sourceFile": "src/modules/auth/auth.routes.ts"
    },
    {
      "method": "POST",
      "path": "/logout-all",
      "fullPath": "/api/auth/logout-all",
      "module": "auth",
      "sourceFile": "src/modules/auth/auth.routes.ts"
    },
    {
      "method": "POST",
      "path": "/register",
      "fullPath": "/api/auth/register",
      "module": "auth",
      "sourceFile": "src/modules/auth/auth.routes.ts"
    },
    {
      "method": "GET",
      "path": "/sessions",
      "fullPath": "/api/auth/sessions",
      "module": "auth",
      "sourceFile": "src/modules/auth/auth.routes.ts"
    },
    {
      "method": "POST",
      "path": "/sessions",
      "fullPath": "/api/auth/sessions",
      "module": "auth",
      "sourceFile": "src/modules/auth/auth.routes.ts"
    },
    {
      "method": "PATCH",
      "path": "/sessions/:sessionId",
      "fullPath": "/api/auth/sessions/:sessionId",
      "module": "auth",
      "sourceFile": "src/modules/auth/auth.routes.ts"
    },
    {
      "method": "GET",
      "path": "/sessions/manage",
      "fullPath": "/api/auth/sessions/manage",
      "module": "auth",
      "sourceFile": "src/modules/auth/auth.routes.ts"
    },
    {
      "method": "POST",
      "path": "/book-tokens",
      "fullPath": "/api/dining/book-tokens",
      "module": "dining",
      "sourceFile": "src/modules/dining/dining.routes.ts"
    },
    {
      "method": "GET",
      "path": "/bookings/menu/:menuId",
      "fullPath": "/api/dining/bookings/menu/:menuId",
      "module": "dining",
      "sourceFile": "src/modules/dining/dining.routes.ts"
    },
    {
      "method": "GET",
      "path": "/bookings/tomorrow",
      "fullPath": "/api/dining/bookings/tomorrow",
      "module": "dining",
      "sourceFile": "src/modules/dining/dining.routes.ts"
    },
    {
      "method": "PATCH",
      "path": "/cancel-token/:tokenId",
      "fullPath": "/api/dining/cancel-token/:tokenId",
      "module": "dining",
      "sourceFile": "src/modules/dining/dining.routes.ts"
    },
    {
      "method": "GET",
      "path": "/meal-items",
      "fullPath": "/api/dining/meal-items",
      "module": "dining",
      "sourceFile": "src/modules/dining/dining.routes.ts"
    },
    {
      "method": "POST",
      "path": "/meal-items",
      "fullPath": "/api/dining/meal-items",
      "module": "dining",
      "sourceFile": "src/modules/dining/dining.routes.ts"
    },
    {
      "method": "DELETE",
      "path": "/meal-items/:itemId",
      "fullPath": "/api/dining/meal-items/:itemId",
      "module": "dining",
      "sourceFile": "src/modules/dining/dining.routes.ts"
    },
    {
      "method": "PATCH",
      "path": "/meal-items/:itemId",
      "fullPath": "/api/dining/meal-items/:itemId",
      "module": "dining",
      "sourceFile": "src/modules/dining/dining.routes.ts"
    },
    {
      "method": "DELETE",
      "path": "/menu/:menuId",
      "fullPath": "/api/dining/menu/:menuId",
      "module": "dining",
      "sourceFile": "src/modules/dining/dining.routes.ts"
    },
    {
      "method": "PATCH",
      "path": "/menu/:menuId/update",
      "fullPath": "/api/dining/menu/:menuId/update",
      "module": "dining",
      "sourceFile": "src/modules/dining/dining.routes.ts"
    },
    {
      "method": "POST",
      "path": "/menu/create",
      "fullPath": "/api/dining/menu/create",
      "module": "dining",
      "sourceFile": "src/modules/dining/dining.routes.ts"
    },
    {
      "method": "GET",
      "path": "/menus/today",
      "fullPath": "/api/dining/menus/today",
      "module": "dining",
      "sourceFile": "src/modules/dining/dining.routes.ts"
    },
    {
      "method": "GET",
      "path": "/menus/tomorrow",
      "fullPath": "/api/dining/menus/tomorrow",
      "module": "dining",
      "sourceFile": "src/modules/dining/dining.routes.ts"
    },
    {
      "method": "GET",
      "path": "/my-active-tokens",
      "fullPath": "/api/dining/my-active-tokens",
      "module": "dining",
      "sourceFile": "src/modules/dining/dining.routes.ts"
    },
    {
      "method": "GET",
      "path": "/payment/:paymentId",
      "fullPath": "/api/dining/payment/:paymentId",
      "module": "dining",
      "sourceFile": "src/modules/dining/dining.routes.ts"
    },
    {
      "method": "POST",
      "path": "/payment/:paymentId/refund",
      "fullPath": "/api/dining/payment/:paymentId/refund",
      "module": "dining",
      "sourceFile": "src/modules/dining/dining.routes.ts"
    },
    {
      "method": "GET",
      "path": "/report/daily",
      "fullPath": "/api/dining/report/daily",
      "module": "dining",
      "sourceFile": "src/modules/dining/dining.routes.ts"
    },
    {
      "method": "GET",
      "path": "/report/monthly",
      "fullPath": "/api/dining/report/monthly",
      "module": "dining",
      "sourceFile": "src/modules/dining/dining.routes.ts"
    },
    {
      "method": "GET",
      "path": "/report/range",
      "fullPath": "/api/dining/report/range",
      "module": "dining",
      "sourceFile": "src/modules/dining/dining.routes.ts"
    },
    {
      "method": "GET",
      "path": "/token-history",
      "fullPath": "/api/dining/token-history",
      "module": "dining",
      "sourceFile": "src/modules/dining/dining.routes.ts"
    },
    {
      "method": "GET",
      "path": "/token/:tokenId",
      "fullPath": "/api/dining/token/:tokenId",
      "module": "dining",
      "sourceFile": "src/modules/dining/dining.routes.ts"
    },
    {
      "method": "PATCH",
      "path": "/tokens/mark-consumed",
      "fullPath": "/api/dining/tokens/mark-consumed",
      "module": "dining",
      "sourceFile": "src/modules/dining/dining.routes.ts"
    },
    {
      "method": "GET",
      "path": "/tomorrow-menus",
      "fullPath": "/api/dining/tomorrow-menus",
      "module": "dining",
      "sourceFile": "src/modules/dining/dining.routes.ts"
    },
    {
      "method": "POST",
      "path": "/dues",
      "fullPath": "/api/finance/dues",
      "module": "finance",
      "sourceFile": "src/modules/finance/finance.routes.ts"
    },
    {
      "method": "PATCH",
      "path": "/dues/pay/:id",
      "fullPath": "/api/finance/dues/pay/:id",
      "module": "finance",
      "sourceFile": "src/modules/finance/finance.routes.ts"
    },
    {
      "method": "POST",
      "path": "/expense",
      "fullPath": "/api/finance/expense",
      "module": "finance",
      "sourceFile": "src/modules/finance/finance.routes.ts"
    },
    {
      "method": "GET",
      "path": "/expenses",
      "fullPath": "/api/finance/expenses",
      "module": "finance",
      "sourceFile": "src/modules/finance/finance.routes.ts"
    },
    {
      "method": "GET",
      "path": "/meal-payment/:id",
      "fullPath": "/api/finance/meal-payment/:id",
      "module": "finance",
      "sourceFile": "src/modules/finance/finance.routes.ts"
    },
    {
      "method": "PATCH",
      "path": "/meal-payment/:id/verify-receipt",
      "fullPath": "/api/finance/meal-payment/:id/verify-receipt",
      "module": "finance",
      "sourceFile": "src/modules/finance/finance.routes.ts"
    },
    {
      "method": "GET",
      "path": "/meal-payments",
      "fullPath": "/api/finance/meal-payments",
      "module": "finance",
      "sourceFile": "src/modules/finance/finance.routes.ts"
    },
    {
      "method": "GET",
      "path": "/meal-payments/report",
      "fullPath": "/api/finance/meal-payments/report",
      "module": "finance",
      "sourceFile": "src/modules/finance/finance.routes.ts"
    },
    {
      "method": "GET",
      "path": "/my-dues",
      "fullPath": "/api/finance/my-dues",
      "module": "finance",
      "sourceFile": "src/modules/finance/finance.routes.ts"
    },
    {
      "method": "POST",
      "path": "/my-dues/pay/:id",
      "fullPath": "/api/finance/my-dues/pay/:id",
      "module": "finance",
      "sourceFile": "src/modules/finance/finance.routes.ts"
    },
    {
      "method": "GET",
      "path": "/my-ledger",
      "fullPath": "/api/finance/my-ledger",
      "module": "finance",
      "sourceFile": "src/modules/finance/finance.routes.ts"
    },
    {
      "method": "PATCH",
      "path": "/payments/:id/verify-receipt",
      "fullPath": "/api/finance/payments/:id/verify-receipt",
      "module": "finance",
      "sourceFile": "src/modules/finance/finance.routes.ts"
    },
    {
      "method": "GET",
      "path": "/student/ledger/:id",
      "fullPath": "/api/finance/student/ledger/:id",
      "module": "finance",
      "sourceFile": "src/modules/finance/finance.routes.ts"
    },
    {
      "method": "GET",
      "path": "/damage",
      "fullPath": "/api/inventory/damage",
      "module": "inventory",
      "sourceFile": "src/modules/inventory/inventory.routes.ts"
    },
    {
      "method": "POST",
      "path": "/damage",
      "fullPath": "/api/inventory/damage",
      "module": "inventory",
      "sourceFile": "src/modules/inventory/inventory.routes.ts"
    },
    {
      "method": "PATCH",
      "path": "/damage/:id/fix",
      "fullPath": "/api/inventory/damage/:id/fix",
      "module": "inventory",
      "sourceFile": "src/modules/inventory/inventory.routes.ts"
    },
    {
      "method": "PATCH",
      "path": "/damage/:id/verify",
      "fullPath": "/api/inventory/damage/:id/verify",
      "module": "inventory",
      "sourceFile": "src/modules/inventory/inventory.routes.ts"
    },
    {
      "method": "PATCH",
      "path": "/damage/verify/:id",
      "fullPath": "/api/inventory/damage/verify/:id",
      "module": "inventory",
      "sourceFile": "src/modules/inventory/inventory.routes.ts"
    },
    {
      "method": "GET",
      "path": "/rooms",
      "fullPath": "/api/inventory/rooms",
      "module": "inventory",
      "sourceFile": "src/modules/inventory/inventory.routes.ts"
    },
    {
      "method": "POST",
      "path": "/",
      "fullPath": "/api/notifications/",
      "module": "notifications",
      "sourceFile": "src/modules/notifications/notifications.routes.ts"
    },
    {
      "method": "PATCH",
      "path": "/:notificationId/read",
      "fullPath": "/api/notifications/:notificationId/read",
      "module": "notifications",
      "sourceFile": "src/modules/notifications/notifications.routes.ts"
    },
    {
      "method": "GET",
      "path": "/my",
      "fullPath": "/api/notifications/my",
      "module": "notifications",
      "sourceFile": "src/modules/notifications/notifications.routes.ts"
    },
    {
      "method": "PATCH",
      "path": "/change-password",
      "fullPath": "/api/profile/change-password",
      "module": "profile",
      "sourceFile": "src/modules/profile/profile.route.ts"
    },
    {
      "method": "GET",
      "path": "/me",
      "fullPath": "/api/profile/me",
      "module": "profile",
      "sourceFile": "src/modules/profile/profile.route.ts"
    },
    {
      "method": "PATCH",
      "path": "/update",
      "fullPath": "/api/profile/update",
      "module": "profile",
      "sourceFile": "src/modules/profile/profile.route.ts"
    },
    {
      "method": "POST",
      "path": "/upload-image",
      "fullPath": "/api/profile/upload-image",
      "module": "profile",
      "sourceFile": "src/modules/profile/profile.route.ts"
    }
  ],
  "environmentVariables": [
    "ADMIN_URL",
    "BREVO_SMTP_HOST",
    "BREVO_SMTP_PASS",
    "BREVO_SMTP_PORT",
    "BREVO_SMTP_USER",
    "CLOUDINARY_API_KEY",
    "CLOUDINARY_API_SECRET",
    "CLOUDINARY_CLOUD_NAME",
    "DATABASE_URL",
    "EMAIL_FROM",
    "NODE_ENV",
    "PAYMENT_SERVER_URL",
    "PAY_SERVICE_SECRET",
    "PORT",
    "REDIS_URL",
    "SESSION_TTL",
    "STUDENT_URL"
  ],
  "docFiles": {
    "index": "docs/README.md",
    "apiByModule": {
      "auth": "docs/api/auth.md",
      "profile": "docs/api/profile.md",
      "dining": "docs/api/dining.md",
      "admission": "docs/api/admission.md",
      "inventory": "docs/api/inventory.md",
      "finance": "docs/api/finance.md",
      "notifications": "docs/api/notifications.md"
    }
  }
}
